rfd900x/__init__.py
rfd900x-0.0.1.dist-info/LICENSE
rfd900x-0.0.1.dist-info/METADATA
rfd900x-0.0.1.dist-info/WHEEL
rfd900x-0.0.1.dist-info/top_level.txt
rfd900x-0.0.1.dist-info/RECORD
